{"pec deck": {"Workout": "", "Equipment": "", "Position": ""}, "seated ohp:": {"Workout": "", "Equipment": "", "Position": ""}, "french press": {"Workout": "", "Equipment": "", "Position": ""}, "dumbbell chest flys": {"Workout": "", "Equipment": "", "Position": ""}, "dips": {"Workout": "", "Equipment": "", "Position": ""}, "seated row": {"Workout": "", "Equipment": "", "Position": ""}, "ez bar curls": {"Workout": "", "Equipment": "", "Position": ""}, "cable rope curls": {"Workout": "", "Equipment": "", "Position": ""}, "machine shoulder press": {"Workout": "", "Equipment": "", "Position": ""}, "seated quad extensions": {"Workout": "", "Equipment": "", "Position": ""}, "lying hamstring curls": {"Workout": "", "Equipment": "", "Position": ""}, "kettle bell swings": {"Workout": "", "Equipment": "", "Position": ""}, "smart chest press machine": {"Workout": "", "Equipment": "", "Position": ""}, "pec deck chest flys": {"Workout": "", "Equipment": "", "Position": ""}, "pec deck rear delt flys": {"Workout": "", "Equipment": "", "Position": ""}, "standing ohp": {"Workout": "", "Equipment": "", "Position": ""}, "dumbbell flat chest flys": {"Workout": "", "Equipment": "", "Position": ""}, "seated hamstring curls": {"Workout": "", "Equipment": "", "Position": ""}, "hip abductor machine": {"Workout": "", "Equipment": "", "Position": ""}, "hip adductor machine": {"Workout": "", "Equipment": "", "Position": ""}, "leg extensions": {"Workout": "", "Equipment": "", "Position": ""}, "standing machine calf raises": {"Workout": "", "Equipment": "", "Position": ""}, "dumbbell bicep curls": {"Workout": "", "Equipment": "", "Position": ""}, "landmine press": {"Workout": "", "Equipment": "", "Position": ""}, "incline cable flys": {"Workout": "", "Equipment": "", "Position": ""}, "ghr": {"Workout": "", "Equipment": "", "Position": ""}, "close grip push-ups": {"Workout": "", "Equipment": "", "Position": ""}, "ez barbell curls": {"Workout": "", "Equipment": "", "Position": ""}, "hammer curls": {"Workout": "", "Equipment": "", "Position": ""}, "low to high cable crossovers": {"Workout": "", "Equipment": "", "Position": ""}, "overhead cable extensions": {"Workout": "", "Equipment": "", "Position": ""}, "plank": {"Workout": "", "Equipment": "", "Position": ""}, "smart shoulder press": {"Workout": "", "Equipment": "", "Position": ""}, "incline press": {"Workout": "", "Equipment": "", "Position": ""}, "face pulls": {"Workout": "", "Equipment": "", "Position": ""}, "rear delt flys": {"Workout": "", "Equipment": "", "Position": ""}, "push press": {"Workout": "", "Equipment": "", "Position": ""}, "rear delt fly": {"Workout": "", "Equipment": "", "Position": ""}, "low to high cable flys": {"Workout": "", "Equipment": "", "Position": ""}, "ez bar standing curls": {"Workout": "", "Equipment": "", "Position": ""}, "close grip bench": {"Workout": "", "Equipment": "", "Position": ""}, "close grip push up": {"Workout": "", "Equipment": "", "Position": ""}, "log push press": {"Workout": "", "Equipment": "", "Position": ""}, "farmers carry": {"Workout": "", "Equipment": "", "Position": ""}, "ez bar incline curls": {"Workout": "", "Equipment": "", "Position": ""}, "fat grip hammer curls": {"Workout": "", "Equipment": "", "Position": ""}, "cable flys low to high": {"Workout": "", "Equipment": "", "Position": ""}, "dumbbell shoulder press": {"Workout": "", "Equipment": "", "Position": ""}, "clean and jerk": {"Workout": "", "Equipment": "", "Position": ""}, "hi to low cable crossovers": {"Workout": "", "Equipment": "", "Position": ""}, "leg curls": {"Workout": "", "Equipment": "", "Position": ""}, "circus dumbbell": {"Workout": "", "Equipment": "", "Position": ""}, "dead hang": {"Workout": "", "Equipment": "", "Position": ""}, "hamstring curls": {"Workout": "", "Equipment": "", "Position": ""}, "good mornings": {"Workout": "", "Equipment": "", "Position": ""}, "floor press": {"Workout": "", "Equipment": "", "Position": ""}, "reverse ez bar curls": {"Workout": "", "Equipment": "", "Position": ""}, "smart machine shoulder press": {"Workout": "", "Equipment": "", "Position": ""}, "bulgarians": {"Workout": "", "Equipment": "", "Position": ""}, "reverse hypers": {"Workout": "", "Equipment": "", "Position": ""}, "incline french press": {"Workout": "", "Equipment": "", "Position": ""}, "leg press": {"Workout": "", "Equipment": "", "Position": ""}, "dinny lift": {"Workout": "", "Equipment": "", "Position": ""}, "strict shoulder press": {"Workout": "", "Equipment": "", "Position": ""}, "incline dumbbell press": {"Workout": "", "Equipment": "", "Position": ""}, "dumbbell rear delt flys": {"Workout": "", "Equipment": "", "Position": ""}, "dinny": {"Workout": "", "Equipment": "", "Position": ""}, "calf raises": {"Workout": "", "Equipment": "", "Position": ""}, "glute bridge": {"Workout": "", "Equipment": "", "Position": ""}, "shrug": {"Workout": "", "Equipment": "", "Position": ""}, "strict barbell press": {"Workout": "", "Equipment": "", "Position": ""}, "lying machine leg curls": {"Workout": "", "Equipment": "", "Position": ""}, "strict barbell": {"Workout": "", "Equipment": "", "Position": ""}, "pec dec flys": {"Workout": "", "Equipment": "", "Position": ""}, "seated leg curls": {"Workout": "", "Equipment": "", "Position": ""}, "leg raises": {"Workout": "", "Equipment": "", "Position": ""}, "machine chest flys": {"Workout": "", "Equipment": "", "Position": ""}, "machine rear delt flys": {"Workout": "", "Equipment": "", "Position": ""}, "machine chest press": {"Workout": "", "Equipment": "", "Position": ""}, "seated leg extensions": {"Workout": "", "Equipment": "", "Position": ""}, "machine leg press": {"Workout": "", "Equipment": "", "Position": ""}, "machine hip adductor": {"Workout": "", "Equipment": "", "Position": ""}, "machine hip abductor": {"Workout": "", "Equipment": "", "Position": ""}, "quad extensions": {"Workout": "", "Equipment": "", "Position": ""}, "seated barbell strict press": {"Workout": "", "Equipment": "", "Position": ""}, "standing french press": {"Workout": "", "Equipment": "", "Position": ""}, "leg extensions smart machine": {"Workout": "", "Equipment": "", "Position": ""}, "leg curls smart machine": {"Workout": "", "Equipment": "", "Position": ""}, "shoulder press smart machine": {"Workout": "", "Equipment": "", "Position": ""}, "bicep curl smart machine": {"Workout": "", "Equipment": "", "Position": ""}, "hammer hold": {"Workout": "", "Equipment": "", "Position": ""}, "ez bar bicep curls": {"Workout": "", "Equipment": "", "Position": ""}, "close grip neutral grip press": {"Workout": "", "Equipment": "", "Position": ""}, "chest flys": {"Workout": "", "Equipment": "", "Position": ""}, "strict press": {"Workout": "", "Equipment": "", "Position": ""}, "shoulder press": {"Workout": "", "Equipment": "", "Position": ""}, "concentration curls": {"Workout": "", "Equipment": "", "Position": ""}, "close grip incline press": {"Workout": "", "Equipment": "", "Position": ""}, "machine reverse flys": {"Workout": "", "Equipment": "", "Position": ""}, "farmers": {"Workout": "", "Equipment": "", "Position": ""}, "pullups": {"Workout": "", "Equipment": "", "Position": ""}, "odd object carry": {"Workout": "", "Equipment": "", "Position": ""}, "dear delt cable flys": {"Workout": "", "Equipment": "", "Position": ""}, "incline dumbbell": {"Workout": "", "Equipment": "", "Position": ""}, "pull-ups": {"Workout": "", "Equipment": "", "Position": ""}, "deadhang": {"Workout": "", "Equipment": "", "Position": ""}, "husafell": {"Workout": "", "Equipment": "", "Position": ""}, "sally push-ups": {"Workout": "", "Equipment": "", "Position": ""}, "dumbbell incline press": {"Workout": "", "Equipment": "", "Position": ""}, "rope climb pulls": {"Workout": "", "Equipment": "", "Position": ""}, "high to low cable flys": {"Workout": "", "Equipment": "", "Position": ""}, "dumbbell farmers carry": {"Workout": "", "Equipment": "", "Position": ""}, "hercules hold": {"Workout": "", "Equipment": "", "Position": ""}, "seated barbell ohp": {"Workout": "", "Equipment": "", "Position": ""}, "oh barbell press": {"Workout": "", "Equipment": "", "Position": ""}, "seated ohp dumbbell": {"Workout": "", "Equipment": "", "Position": ""}, "shrugs": {"Workout": "", "Equipment": "", "Position": ""}, "hanging toes to bar": {"Workout": "", "Equipment": "", "Position": ""}, "dumbbell curls": {"Workout": "", "Equipment": "", "Position": ""}, "dumbbell over head press": {"Workout": "", "Equipment": "", "Position": ""}, "side bends": {"Workout": "", "Equipment": "", "Position": ""}, "deadhangs": {"Workout": "", "Equipment": "", "Position": ""}, "bicep curls": {"Workout": "", "Equipment": "", "Position": ""}, "crunches": {"Workout": "", "Equipment": "", "Position": ""}, "dumbbell hammer curls": {"Workout": "", "Equipment": "", "Position": ""}, "dumbbell shrug": {"Workout": "", "Equipment": "", "Position": ""}, "flutter kicks": {"Workout": "", "Equipment": "", "Position": ""}, "lying leg curl": {"Workout": "", "Equipment": "", "Position": ""}, "hip adductors": {"Workout": "", "Equipment": "", "Position": ""}, "shoulder 3 ways": {"Workout": "", "Equipment": "", "Position": ""}, "log clean": {"Workout": "", "Equipment": "", "Position": ""}, "strict axle ohp": {"Workout": "", "Equipment": "", "Position": ""}, "cable rear delt extensions": {"Workout": "", "Equipment": "", "Position": ""}, "log cleans": {"Workout": "", "Equipment": "", "Position": ""}, "incline dumbbell curls": {"Workout": "", "Equipment": "", "Position": ""}, "lying leg curls": {"Workout": "", "Equipment": "", "Position": ""}, "frame carry": {"Workout": "", "Equipment": "", "Position": ""}, "dumbbell french press": {"Workout": "", "Equipment": "", "Position": ""}, "cable low to high flys": {"Workout": "", "Equipment": "", "Position": ""}, "flex bar shoulder press": {"Workout": "", "Equipment": "", "Position": ""}, "ssb good mornings": {"Workout": "", "Equipment": "", "Position": ""}, "dumbbell side bends": {"Workout": "", "Equipment": "", "Position": ""}, "machine quad extensions": {"Workout": "", "Equipment": "", "Position": ""}, "cable rope bicep curls": {"Workout": "", "Equipment": "", "Position": ""}, "powell raise": {"Workout": "", "Equipment": "", "Position": ""}, "axle push press": {"Workout": "", "Equipment": "", "Position": ""}, "fingal fingers": {"Workout": "", "Equipment": "", "Position": ""}, "russian twists": {"Workout": "", "Equipment": "", "Position": ""}, "kettle bell presses": {"Workout": "", "Equipment": "", "Position": ""}, "banded clams": {"Workout": "", "Equipment": "", "Position": ""}, "prowler push": {"Workout": "", "Equipment": "", "Position": ""}, "monster walks": {"Workout": "", "Equipment": "", "Position": ""}, "banded pull aparts": {"Workout": "", "Equipment": "", "Position": ""}, "camber bar push press": {"Workout": "", "Equipment": "", "Position": ""}, "dumbbell pull overs": {"Workout": "", "Equipment": "", "Position": ""}, "kettle bell press": {"Workout": "", "Equipment": "", "Position": ""}, "log strict press": {"Workout": "", "Equipment": "", "Position": ""}, "carry medley": {"Workout": "", "Equipment": "", "Position": ""}, "conan\u2019s wheel": {"Workout": "", "Equipment": "", "Position": ""}, "clams": {"Workout": "", "Equipment": "", "Position": ""}, "field goals": {"Workout": "", "Equipment": "", "Position": ""}, "axle overhead holds": {"Workout": "", "Equipment": "", "Position": ""}, "fire hydrants": {"Workout": "", "Equipment": "", "Position": ""}, "axle press": {"Workout": "", "Equipment": "", "Position": ""}, "husafell carry": {"Workout": "", "Equipment": "", "Position": ""}, "leg curl": {"Workout": "", "Equipment": "", "Position": ""}, "standing dumbbell ohp": {"Workout": "", "Equipment": "", "Position": ""}, "goal posts": {"Workout": "", "Equipment": "", "Position": ""}, "camber bar zpress": {"Workout": "", "Equipment": "", "Position": ""}, "push ups": {"Workout": "", "Equipment": "", "Position": ""}, "dumbbell standing ohp": {"Workout": "", "Equipment": "", "Position": ""}, "husafell picks": {"Workout": "", "Equipment": "", "Position": ""}, "axles press": {"Workout": "", "Equipment": "", "Position": ""}, "standing dumbbell overhead press": {"Workout": "", "Equipment": "", "Position": ""}, "chain drag": {"Workout": "", "Equipment": "", "Position": ""}, "cross carry": {"Workout": "", "Equipment": "", "Position": ""}, "overhead hold": {"Workout": "", "Equipment": "", "Position": ""}, "odd object": {"Workout": "", "Equipment": "", "Position": ""}}